{
  "id": "aws-security/iam-best-practices",
  "title": "IAM Best Practices",
  "description": "AWS Identity and Access Management (IAM) is a fundamental service for securing your AWS environment. This guide covers best practices for managing identities and access in AWS.",
  "source": "@site/docs/aws-security/iam-best-practices.md",
  "sourceDirName": "aws-security",
  "slug": "/aws-security/iam-best-practices",
  "permalink": "/docs/aws-security/iam-best-practices",
  "draft": false,
  "unlisted": false,
  "editUrl": "https://github.com/ThopuriSeetaramaiah/k8s-security-docs/tree/main/docs/aws-security/iam-best-practices.md",
  "tags": [],
  "version": "current",
  "sidebarPosition": 3,
  "frontMatter": {
    "sidebar_position": 3
  },
  "sidebar": "tutorialSidebar",
  "previous": {
    "title": "AWS Security Foundations",
    "permalink": "/docs/aws-security/foundations"
  },
  "next": {
    "title": "DevSecOps Introduction",
    "permalink": "/docs/devops-security/intro"
  }
}